LICENSE
MANIFEST.in
README.md
setup.py
dash_bio/AlignmentChart.py
dash_bio/Circos.py
dash_bio/FornaContainer.py
dash_bio/Ideogram.py
dash_bio/Igv.py
dash_bio/Jsme.py
dash_bio/Molecule2dViewer.py
dash_bio/Molecule3dViewer.py
dash_bio/NeedlePlot.py
dash_bio/NglMoleculeViewer.py
dash_bio/OncoPrint.py
dash_bio/Pileup.py
dash_bio/SequenceViewer.py
dash_bio/Speck.py
dash_bio/__init__.py
dash_bio/_imports_.py
dash_bio/async-alignment.js
dash_bio/async-alignment.js.map
dash_bio/async-circos.js
dash_bio/async-circos.js.map
dash_bio/async-ideogram.js
dash_bio/async-ideogram.js.map
dash_bio/async-igv.js
dash_bio/async-igv.js.map
dash_bio/async-jsme.js
dash_bio/async-jsme.js.map
dash_bio/async-moleculeviewer2.js
dash_bio/async-moleculeviewer2.js.map
dash_bio/async-moleculeviewer3.js
dash_bio/async-moleculeviewer3.js.map
dash_bio/async-needle.js
dash_bio/async-needle.js.map
dash_bio/async-nglmoleculeviewer.js
dash_bio/async-nglmoleculeviewer.js.map
dash_bio/async-onco.js
dash_bio/async-onco.js.map
dash_bio/async-pileup.js
dash_bio/async-pileup.js.map
dash_bio/async-sequence.js
dash_bio/async-sequence.js.map
dash_bio/async-speck.js
dash_bio/async-speck.js.map
dash_bio/bundle.js
dash_bio/bundle.js.map
dash_bio/dash_bio-shared.js
dash_bio/dash_bio-shared.js.map
dash_bio/metadata.json
dash_bio/package-info.json
dash_bio.egg-info/PKG-INFO
dash_bio.egg-info/SOURCES.txt
dash_bio.egg-info/dependency_links.txt
dash_bio.egg-info/requires.txt
dash_bio.egg-info/top_level.txt
dash_bio/component_factory/__init__.py
dash_bio/component_factory/_clustergram.py
dash_bio/component_factory/_manhattan.py
dash_bio/component_factory/_variant.py
dash_bio/component_factory/_volcano.py
dash_bio/component_factory/utils.py
dash_bio/utils/__init__.py
dash_bio/utils/chem_structure_reader.py
dash_bio/utils/circos_parser.py
dash_bio/utils/gene_expression_reader.py
dash_bio/utils/mol3dviewer_styles_creator.py
dash_bio/utils/mutation_data_parser.py
dash_bio/utils/ngl_parser.py
dash_bio/utils/pdb_parser.py
dash_bio/utils/protein_reader.py
dash_bio/utils/uniprot_database_tools.py
dash_bio/utils/xyz_reader.py