Metadata-Version: 2.1
Name: dash-bio
Version: 1.0.1
Summary: Dash components for bioinformatics
Home-page: http://github.com/plotly/dash-bio
Author: The Plotly Team <dashbio@plotly.com>
Author-email: dashbio@plotly.com
License: UNKNOWN
Platform: UNKNOWN
Classifier: Programming Language :: Python :: 3
Classifier: License :: OSI Approved :: MIT License
Classifier: Operating System :: OS Independent
License-File: LICENSE
